yta_video_ffmpeg/__init__.py
yta_video_ffmpeg/command.py
yta_video_ffmpeg/flag.py
yta_video_ffmpeg/handler.py
yta_video_ffmpeg/metadata.py
yta_video_ffmpeg/reader.py
yta_video_ffmpeg-0.0.19.dist-info/licenses/LICENSE
yta_video_ffmpeg-0.0.19.dist-info/METADATA
yta_video_ffmpeg-0.0.19.dist-info/WHEEL
yta_video_ffmpeg-0.0.19.dist-info/RECORD
