Metadata-Version: 2.4
Name: yta-video-ffmpeg
Version: 0.0.19
Summary: Youtube Autonomous Video Ffmpeg Module
License-File: LICENSE
Author: danialcala94
Author-email: danielalcalavalera@gmail.com
Requires-Python: ==3.9
Classifier: Programming Language :: Python :: 3
Classifier: Programming Language :: Python :: 3.9
Requires-Dist: yta_constants (>=0.0.1,<1.0.0)
Requires-Dist: yta_file (>=0.0.1,<1.0.0)
Requires-Dist: yta_image_utils (>=0.0.1,<1.0.0)
Requires-Dist: yta_math (>=0.0.1,<1.0.0)
Requires-Dist: yta_positioning (>=0.0.1,<1.0.0)
Requires-Dist: yta_programming (>=0.0.1,<1.0.0)
Requires-Dist: yta_temp (>=0.0.1,<1.0.0)
Requires-Dist: yta_validation (>=0.0.1,<1.0.0)
